determinagent/__init__.py
determinagent/adapters/__init__.py
determinagent/adapters/base.py
determinagent/adapters/claude.py
determinagent/adapters/codex.py
determinagent/adapters/copilot.py
determinagent/adapters/gemini.py
determinagent/agent.py
determinagent/cli_utils.py
determinagent/config.py
determinagent/constants.py
determinagent/exceptions.py
determinagent/parsers.py
determinagent/py.typed
determinagent/sessions.py
determinagent/ui.py
determinagent/utils.py
determinagent/validation.py
determinagent-0.14.1.dist-info/METADATA
determinagent-0.14.1.dist-info/WHEEL
determinagent-0.14.1.dist-info/licenses/LICENSE
determinagent-0.14.1.dist-info/RECORD
