Metadata-Version: 2.4
Name: determinagent
Version: 0.14.1
Summary: CLI-First deterministic multi-agent orchestration library
License: Apache-2.0
License-File: LICENSE
Keywords: ai,agents,cli,orchestration,langgraph
Author: DeterminAgent Team
Author-email: victor@experto.ai
Requires-Python: >=3.10,<4.0
Classifier: Development Status :: 3 - Alpha
Classifier: Intended Audience :: Developers
Classifier: License :: OSI Approved :: Apache Software License
Classifier: Programming Language :: Python :: 3
Classifier: Programming Language :: Python :: 3.10
Classifier: Programming Language :: Python :: 3.11
Classifier: Programming Language :: Python :: 3.12
Classifier: Programming Language :: Python :: 3.13
Classifier: Programming Language :: Python :: 3.14
Classifier: Topic :: Scientific/Engineering :: Artificial Intelligence
Classifier: Topic :: Software Development :: Libraries :: Python Modules
Requires-Dist: beautifulsoup4 (>=4.9.0)
Requires-Dist: langgraph (>=1.0.0)
Requires-Dist: markdown (>=3.0)
Requires-Dist: pydantic (>=2.0)
Requires-Dist: pyyaml (>=6.0)
Project-URL: Documentation, https://github.com/Experto-AI/determinagent#readme
Project-URL: Homepage, https://github.com/Experto-AI/determinagent
Project-URL: Issues, https://github.com/Experto-AI/determinagent/issues
Project-URL: Repository, https://github.com/Experto-AI/determinagent
